img64/__init__.py
img64/convert.py
img64-1.2.1.dist-info/LICENSE
img64-1.2.1.dist-info/METADATA
img64-1.2.1.dist-info/WHEEL
img64-1.2.1.dist-info/top_level.txt
img64-1.2.1.dist-info/RECORD
