Metadata-Version: 2.1
Name: img64
Version: 1.2.1
Summary: This library is a tool for converting images to base64 encoding and vice versa.
Home-page: https://github.com/gibiee/img64
Download-URL: 
Author: gibiee
Author-email: gibiee@naver.com
License: MIT
Keywords: image,base64,image_base64
Classifier: Programming Language :: Python :: 3
Classifier: License :: OSI Approved :: MIT License
Classifier: Operating System :: OS Independent
Requires-Python: >=3
License-File: LICENSE
Requires-Dist: pillow
Requires-Dist: numpy
